README.md
setup.py
odit/__init__.py
odit/cli.py
odit/odit.py
odit.egg-info/PKG-INFO
odit.egg-info/SOURCES.txt
odit.egg-info/dependency_links.txt
odit.egg-info/entry_points.txt
odit.egg-info/requires.txt
odit.egg-info/top_level.txt