Metadata-Version: 1.0
Name: odit
Version: 0.1.6
Summary: Document as code, This prototype is an example to show how build document can be generated programmatically 
Home-page: https://theecodedragon.com
Author: theecodedragon
Author-email: theecodedragon@gmail.com
License: Apache License 2.0
Platform: UNKNOWN
